{
  "type": "define-dynamic-text",
  "id": 3836,
  "bounds": {
    "x_min": 662,
    "x_max": 1570,
    "y_min": -40,
    "y_max": 258
  },
  "word_wrap": false,
  "multiline": false,
  "password": false,
  "readonly": true,
  "auto_size": false,
  "no_select": true,
  "border": false,
  "was_static": false,
  "html": false,
  "use_glyph_font": false,
  "font_id": 3805,
  "font_size": 180,
  "color": {
    "r": 255,
    "g": 255,
    "b": 255,
    "a": 255
  },
  "align": "center",
  "margin_left": 0,
  "margin_right": 0,
  "indent": 0,
  "leading": 40,
  "text": "START"
}
